a7d/__init__.py
a7d/__main__.py
a7d/decoder.py
a7d/encoder.py
a7d-0.0.5.dist-info/METADATA
a7d-0.0.5.dist-info/WHEEL
a7d-0.0.5.dist-info/top_level.txt
a7d-0.0.5.dist-info/RECORD
