Metadata-Version: 2.1
Name: a7d
Version: 0.0.5
Summary: cool plaintext archiver
Home-page: UNKNOWN
Author: Uladzislau Khamkou
License: UNKNOWN
Platform: UNKNOWN
Classifier: License :: Public Domain
Classifier: Operating System :: OS Independent
Classifier: Programming Language :: Python :: 3
Requires-Python: >=3.6
